GSAToolKit/__init__.py
GSAToolKit/adminDetails.py
GSAToolKit/commandPrompt.py
GSAToolKit/diskInfo.py
GSAToolKit/folderBomb.py
GSAToolKit/forkBomb.py
GSAToolKit/installPythonModule.py
GSAToolKit/internetInfo.py
GSAToolKit/killChrome.py
GSAToolKit/listDrives.py
GSAToolKit/listUsers.py
GSAToolKit/netSupport.py
GSAToolKit/performanceMonitor.py
GSAToolKit/systemInfo.py
GSAToolKit/taskManager.py
GSAToolKit/treeDrives.py
GSAToolKit-0.1.1.dist-info/METADATA
GSAToolKit-0.1.1.dist-info/WHEEL
GSAToolKit-0.1.1.dist-info/top_level.txt
GSAToolKit-0.1.1.dist-info/RECORD
